LICENSE
MANIFEST.in
README.rst
VERSION
setup.py
phial/__init__.py
phial/__main__.py
phial/documents.py
phial/exceptions.py
phial/pages.py
phial/processor.py
phial/tool.py
phial/utils.py
phial.egg-info/PKG-INFO
phial.egg-info/SOURCES.txt
phial.egg-info/dependency_links.txt
phial.egg-info/entry_points.txt
phial.egg-info/requires.txt
phial.egg-info/top_level.txt
phial.egg-info/zip-safe
phial/tests/__init__.py
phial/tests/test_documents.py