Metadata-Version: 1.1
Name: phial
Version: 0.2.0
Summary: A static website generator that takes motivation from Flask and Jekyll.
Home-page: https://www.github.com/brownhead/phial
Author: John Sullivan and other contributers
Author-email: john@galahgroup.com
License: Apache v2.0
Keywords: python ssg
Platform: UNKNOWN
Classifier: Development Status :: 4 - Beta
Classifier: Intended Audience :: Developers
Classifier: License :: OSI Approved :: Apache Software License
